linkture-4.7.1.dist-info/METADATA
linkture-4.7.1.dist-info/WHEEL
linkture-4.7.1.dist-info/entry_points.txt
linkture-4.7.1.dist-info/licenses/LICENSE
linkture/__init__.py
linkture/__main__.py
linkture/linkture.py
linkture/res/custom.json
linkture/res/resources.db
linkture-4.7.1.dist-info/RECORD
