Metadata-Version: 2.1
Name: linkture
Version: 4.7.1
Summary: PARSE and PROCESS BIBLE SCRIPTURE REFERENCES: extract, tag, link, rewrite, translate, BCV-encode and decode
Keywords: bible,scriptures,scripture-references,scripture-translation,scripture-parser,scripture-linker
Author-Email: "Eryk J." <infiniti@inventati.org>
License: MIT
Classifier: License :: OSI Approved :: MIT License
Classifier: Operating System :: OS Independent
Classifier: Programming Language :: Python :: 3.9
Classifier: Programming Language :: Python :: 3.10
Classifier: Programming Language :: Python :: 3.11
Classifier: Programming Language :: Python :: 3.12
Classifier: Programming Language :: Python :: 3.13
Classifier: Development Status :: 5 - Production/Stable
Classifier: Environment :: Console
Classifier: Topic :: Religion
Classifier: Topic :: Text Processing :: General
Classifier: Topic :: Text Processing :: Linguistic
Project-URL: Homepage, https://github.com/erykjj/linkture
Project-URL: Issues, https://github.com/erykjj/linkture/issues
Requires-Python: >=3.9
Requires-Dist: setuptools>=59.6.0
Requires-Dist: argparse>=1.4.0
Requires-Dist: regex>=2023.8.8
Requires-Dist: unidecode>=1.3.8
Requires-Dist: pathlib>=1.0.1
